pdxtra.py
pdxtra-1.0.2.dist-info/LICENSE
pdxtra-1.0.2.dist-info/METADATA
pdxtra-1.0.2.dist-info/WHEEL
pdxtra-1.0.2.dist-info/top_level.txt
pdxtra-1.0.2.dist-info/RECORD
