Metadata-Version: 2.1
Name: pdxtra
Version: 1.0.2
Summary: Pandas with time-series data analysis in mind.
License: GNU GENERAL PUBLIC LICENSE
Requires-Python: >=3.10.4
License-File: LICENSE
Requires-Dist: numpy (>=1.22.3)
Requires-Dist: pandas (>=1.4.2)
